linearmoney/__init__.py
linearmoney/_utils.py
linearmoney/cache.py
linearmoney/cldr_version.json
linearmoney/currencies.json
linearmoney/data.py
linearmoney/exceptions.py
linearmoney/locales.json
linearmoney/mixins.py
linearmoney/py.typed
linearmoney/resources.py
linearmoney/scalar.py
linearmoney/supported_iso_codes.json
linearmoney/vector.py
linearmoney/ext/__init__.py
linearmoney/ext/sqlalchemy.py
linearmoney-0.2.1.dist-info/METADATA
linearmoney-0.2.1.dist-info/WHEEL
linearmoney-0.2.1.dist-info/licenses/LICENSE
linearmoney-0.2.1.dist-info/RECORD
