Metadata-Version: 2.3
Name: linearmoney
Version: 0.2.1
Summary: Full multi-currency support for python.
Project-URL: homepage, https://github.com/GrammAcc/linearmoney
Project-URL: bug_tracker, https://github.com/GrammAcc/linearmoney/issues
Project-URL: documentation, https://grammacc.github.io/linearmoney
Project-URL: repository, https://github.com/GrammAcc/linearmoney
Author-email: GrammAcc <grammaticallyacceptable@grammacc.dev>
Maintainer-email: GrammAcc <grammaticallyacceptable@grammacc.dev>
License-Expression: MIT
License-File: LICENSE
Keywords: currency,fintech,forex,framework,money
Classifier: Development Status :: 3 - Alpha
Requires-Python: >=3.10
Provides-Extra: dev
Requires-Dist: pytest; extra == 'dev'
Requires-Dist: pytest-lazy-fixtures; extra == 'dev'
Requires-Dist: pytest-parametrize-cases; extra == 'dev'
Provides-Extra: sqlalchemy
Requires-Dist: sqlalchemy; extra == 'sqlalchemy'
